msn/__init__.py
msn/client.py
msn/core/__init__.py
msn/message/__init__.py
msn/message/actions.py
msn/message/base.py
msn/message/enums.py
msn/message/quick_replies.py
msn/message/raw.py
msn/message/templates.py
msn/nlp/__init__.py
msn/page/__init__.py
msn/page/enums.py
msn/profile/__init__.py
msn/token/__init__.py
msn/user/__init__.py
msn/utils/__init__.py
msn/utils/urls.py
msn-1.0.5.dist-info/WHEEL
msn-1.0.5.dist-info/METADATA
msn-1.0.5.dist-info/RECORD
