Metadata-Version: 2.1
Name: msn
Version: 1.0.5
Summary: 
Author: Oscar Giraldo Castillo
Author-email: oscar.gi.cast@gmail.com
Requires-Python: >=3.5,<4.0
Classifier: Programming Language :: Python :: 3
Classifier: Programming Language :: Python :: 3.5
Classifier: Programming Language :: Python :: 3.6
Classifier: Programming Language :: Python :: 3.7
Classifier: Programming Language :: Python :: 3.8
Classifier: Programming Language :: Python :: 3.9
Requires-Dist: requests (>=2.24,<3.0)
